{
    "students": [
        {
            "name": "Alice Adams",
            "student_id": 2001,
            "major": "Computer Science",
            "grade": "A"
        },
        {
            "name": "Benjamin Brown",
            "student_id": 2002,
            "major": "Engineering",
            "grade": "B+"
        },
        {
            "name": "Catherine Clark",
            "student_id": 2003,
            "major": "Mathematics",
            "grade": "A-"
        },
        {
            "name": "David Davis",
            "student_id": 2004,
            "major": "Biology",
            "grade": "B"
        },
        {
            "name": "Emma Evans",
            "student_id": 2005,
            "major": "History",
            "grade": "A"
        },
        {
            "name": "Frank Foster",
            "student_id": 2006,
            "major": "Psychology",
            "grade": "B-"
        },
        {
            "name": "Grace Green",
            "student_id": 2007,
            "major": "Sociology",
            "grade": "C+"
        },
        {
            "name": "Henry Harris",
            "student_id": 2008,
            "major": "English",
            "grade": "B"
        },
        {
            "name": "Isabel Inman",
            "student_id": 2009,
            "major": "Art",
            "grade": "A+"
        },
        {
            "name": "James Johnson",
            "student_id": 2010,
            "major": "Economics",
            "grade": "B-"
        }
    ]
}